hanko_sdk/__init__.py
hanko_sdk/auth.py
hanko_sdk/client.py
hanko_sdk/config.py
hanko_sdk/json_serializer.py
hanko_sdk/exceptions/__init__.py
hanko_sdk/exceptions/hanko_exceptions.py
hanko_sdk/models/__init__.py
hanko_sdk/models/assertion.py
hanko_sdk/models/attachment.py
hanko_sdk/models/attestation.py
hanko_sdk/models/authentication_finalization.py
hanko_sdk/models/authentication_initialization.py
hanko_sdk/models/authenticator.py
hanko_sdk/models/base64_entities.py
hanko_sdk/models/base_model.py
hanko_sdk/models/challenge.py
hanko_sdk/models/core.py
hanko_sdk/models/credential.py
hanko_sdk/models/credential_query.py
hanko_sdk/models/credential_update.py
hanko_sdk/models/datetime_model.py
hanko_sdk/models/entities.py
hanko_sdk/models/options.py
hanko_sdk/models/registration_finalization.py
hanko_sdk/models/registration_initialization.py
hanko_sdk/models/transaction_finalization.py
hanko_sdk/models/transaction_initialization.py
hanko_sdk/models/webauthn_cose.py
hanko_sdk/utils/__init__.py
hanko_sdk/utils/base64_utils.py
hanko_sdk/utils/hmac_utils.py
hanko_sdk/utils/url_utils.py
hanko_sdk-1.0.1.dist-info/LICENSE
hanko_sdk-1.0.1.dist-info/METADATA
hanko_sdk-1.0.1.dist-info/WHEEL
hanko_sdk-1.0.1.dist-info/top_level.txt
hanko_sdk-1.0.1.dist-info/RECORD
