Metadata-Version: 2.1
Name: hanko-sdk
Version: 1.0.1
Summary: API client for communicating with the Hanko Authentication API, enabling WebAuthn authentication for your project
Home-page: https://github.com/teamhanko/hanko-python
Author: Hanko
Author-email: jan.gerle@hanko.io
License: UNKNOWN
Project-URL: Bug Tracker, https://github.com/teamhanko/hanko-python/issues
Platform: UNKNOWN
Classifier: Programming Language :: Python :: 3
Classifier: License :: OSI Approved :: Apache Software License
Classifier: Operating System :: OS Independent
Classifier: Development Status :: 5 - Production/Stable
Classifier: Environment :: Web Environment
Classifier: Intended Audience :: Developers
Classifier: Topic :: Communications :: FIDO
Classifier: Topic :: Security
Requires-Python: >=3.7
License-File: LICENSE
Requires-Dist: requests
Requires-Dist: python-dateutil
Requires-Dist: enforce-typing
